hass_auth_synology/__init__.py
hass_auth_synology/install.py
hass_auth_synology/synology.py
hass_auth_synology-0.4.28.dist-info/entry_points.txt
hass_auth_synology-0.4.28.dist-info/LICENSE
hass_auth_synology-0.4.28.dist-info/WHEEL
hass_auth_synology-0.4.28.dist-info/METADATA
hass_auth_synology-0.4.28.dist-info/RECORD
