Metadata-Version: 2.1
Name: hass-auth-synology
Version: 0.4.28
Summary: Synology authentication provider for Home Assistant
Home-page: https://github.com/sdebruyn/hass-auth-synology
License: Apache-2.0
Keywords: synology,authentication,homeassistant,hass
Author: Sam Debruyn
Author-email: sam@debruyn.dev
Requires-Python: >=3.9,<4.0
Classifier: Development Status :: 4 - Beta
Classifier: Intended Audience :: Developers
Classifier: Intended Audience :: End Users/Desktop
Classifier: License :: OSI Approved :: Apache Software License
Classifier: Operating System :: OS Independent
Classifier: Programming Language :: Python :: 3
Classifier: Programming Language :: Python :: 3.10
Classifier: Programming Language :: Python :: 3.9
Classifier: Topic :: Home Automation
Classifier: Topic :: Security
Requires-Dist: homeassistant (>=2022.6.0,<2023.0.0)
Project-URL: Repository, https://github.com/sdebruyn/hass-auth-synology
